ticfinder/__init__.py
ticfinder/ticfinder.py
ticfinder-0.1.1.dist-info/LICENSE
ticfinder-0.1.1.dist-info/WHEEL
ticfinder-0.1.1.dist-info/METADATA
ticfinder-0.1.1.dist-info/RECORD
